{
    "Name": "CCTVBehavior",
    "CCTVBehavior": {
        "Active": true,
        "RotateSpeed": 0.0,
        "MaxRotation": 0.0,
        "RotateDirection": -1.0
    },
    "Transform": {
        "translation": [ -0.2, 0.6, 0 ],
        "scale": [ 0.2, 0.2, 0 ],
        "rotation": 0
    },
    "Sprite": {
        "tex_path": "./Assets/PROP_CCTV_Asset_002.png",
        "z_priority": -2
    },
    "Physics": {
        "acceleration": [ 0.0, 0.0, 0 ],
        "velocity": [ 0, 0, 0 ]
    },
    "Detection": {
        "tex_path": "./Assets/UI_Status_Seen_002.png",
        "tex_path2": "./Assets/UI_Status_Caught_002.png"
    },
    "Vision": {
        "Angle": 0,
        "Distance": 4.0,
        "FOV": 90
    }
}
